AUTHORS.rst
CHANGELOG.md
CONTRIBUTING.rst
LICENSE
MANIFEST.in
README.md
setup.cfg
setup.py
clinvar_api/__init__.py
clinvar_api/client.py
clinvar_api/common.py
clinvar_api/constants.py
clinvar_api/exceptions.py
clinvar_api/py.typed
clinvar_api/models/__init__.py
clinvar_api/models/query_response.py
clinvar_api/models/sub_payload.py
clinvar_api/models/sub_response.py
clinvar_api/msg/__init__.py
clinvar_api/msg/query_response.py
clinvar_api/msg/sub_payload.py
clinvar_api/msg/sub_response.py
clinvar_api/schemas/__init__.py
clinvar_api/schemas/submission_schema.json
clinvar_api/schemas/summary_response_schema.json
clinvar_data/__init__.py
clinvar_data/class_by_freq.py
clinvar_data/extract_vars.py
clinvar_data/gene_impact.py
clinvar_data/phenotype_link.py
clinvar_data/py.typed
clinvar_data/conversion/__init__.py
clinvar_data/conversion/dict_to_pb.py
clinvar_data/conversion/normalize.py
clinvar_data/conversion/normalizer.py
clinvar_data/pbs/__init__.py
clinvar_data/pbs/class_by_freq.py
clinvar_data/pbs/class_by_freq_pb2.py
clinvar_data/pbs/class_by_freq_pb2.pyi
clinvar_data/pbs/clinvar_public.py
clinvar_data/pbs/clinvar_public_pb2.py
clinvar_data/pbs/clinvar_public_pb2.pyi
clinvar_data/pbs/extracted_vars.py
clinvar_data/pbs/extracted_vars_pb2.py
clinvar_data/pbs/extracted_vars_pb2.pyi
clinvar_data/pbs/gene_impact.py
clinvar_data/pbs/gene_impact_pb2.py
clinvar_data/pbs/gene_impact_pb2.pyi
clinvar_data/pbs/phenotype_link.py
clinvar_data/pbs/phenotype_link_pb2.py
clinvar_data/pbs/phenotype_link_pb2.pyi
clinvar_data/pbs/clinvar_this/__init__.py
clinvar_this/__init__.py
clinvar_this/batches.py
clinvar_this/cli.py
clinvar_this/config.py
clinvar_this/exceptions.py
clinvar_this/py.typed
clinvar_this/version.py
clinvar_this.egg-info/PKG-INFO
clinvar_this.egg-info/SOURCES.txt
clinvar_this.egg-info/dependency_links.txt
clinvar_this.egg-info/entry_points.txt
clinvar_this.egg-info/not-zip-safe
clinvar_this.egg-info/requires.txt
clinvar_this.egg-info/top_level.txt
clinvar_this/io/__init__.py
clinvar_this/io/tsv.py
docs/Makefile
docs/api_vs_cli.rst
docs/authors.rst
docs/cli.rst
docs/common_errors.rst
docs/conf.py
docs/contributing.rst
docs/file_formats.rst
docs/getting_started.rst
docs/history.rst
docs/index.rst
docs/installation.rst
