Metadata-Version: 2.1
Name: clinvar-this
Version: 0.18.4
Summary: ClinVar Submission via API Made Easy
Home-page: https://github.com/bihealth/clinvar-this
Author: Manuel Holtgrewe
Author-email: manuel.holtgrewe@bih-charite.de
License: MIT license
Keywords: clinvar
Classifier: Development Status :: 2 - Pre-Alpha
Classifier: Intended Audience :: Developers
Classifier: License :: OSI Approved :: MIT License
Classifier: Natural Language :: English
Classifier: Programming Language :: Python :: 3
Classifier: Programming Language :: Python :: 3.10
Classifier: Programming Language :: Python :: 3.11
Classifier: Programming Language :: Python :: 3.12
Requires-Python: >=3.6
License-File: LICENSE
License-File: AUTHORS.rst
